mcp_server_iam/__init__.py
mcp_server_iam/__main__.py
mcp_server_iam/config.py
mcp_server_iam/context.py
mcp_server_iam/logging.py
mcp_server_iam/prompt.py
mcp_server_iam/server.py
mcp_server_iam/server_http.py
mcp_server_iam/tool.py
mcp_server_iam/utils.py
iam_mcp_server-2.4.2.dist-info/METADATA
iam_mcp_server-2.4.2.dist-info/WHEEL
iam_mcp_server-2.4.2.dist-info/entry_points.txt
iam_mcp_server-2.4.2.dist-info/licenses/LICENSE
iam_mcp_server-2.4.2.dist-info/RECORD
