Metadata-Version: 2.4
Name: iam-mcp-server
Version: 2.4.2
Summary: Individual Application Mesh, MCP Server
Project-URL: Homepage, https://github.com/alejandrogarcia-hub/iam-mcp-server
Project-URL: Repository, https://github.com/alejandrogarcia-hub/iam-mcp-server
Project-URL: Issues, https://github.com/alejandrogarcia-hub/iam-mcp-server/issues
Author: Alejandro Garcia
Maintainer-email: Alejandro Garcia <github_dev.chowder574@passmail.net>
License: MIT
License-File: LICENSE
Keywords: automation,git,jobs,mcp,resume,server
Classifier: Development Status :: 4 - Beta
Classifier: License :: OSI Approved :: MIT License
Classifier: Programming Language :: Python :: 3
Classifier: Programming Language :: Python :: 3.11
Requires-Python: >=3.11
Requires-Dist: mcp[cli]>=1.10.1
Requires-Dist: pydantic-core>=2.33.0
Requires-Dist: pydantic-settings>=2.10.1
Requires-Dist: pydantic>=2.11.7
Requires-Dist: python-dotenv>=1.1.1
Requires-Dist: python-json-logger>=3.3.0
Requires-Dist: requests>=2.32.4
Requires-Dist: tenacity>=9.1.2
